bigrest/__init__.py
bigrest/big.py
bigrest/bigip.py
bigrest/bigiq.py
bigrest/version.py
bigrest/common/__init__.py
bigrest/common/constants.py
bigrest/common/debug.py
bigrest/common/exceptions.py
bigrest/common/restobject.py
bigrest/utils/__init__.py
bigrest/utils/utils.py
bigrest-1.7.3.dist-info/LICENSE
bigrest-1.7.3.dist-info/METADATA
bigrest-1.7.3.dist-info/WHEEL
bigrest-1.7.3.dist-info/top_level.txt
bigrest-1.7.3.dist-info/RECORD
