Metadata-Version: 2.1
Name: bigrest
Version: 1.7.3
Summary: A Python SDK for F5 iControl REST API
Home-page: https://github.com/leonardobdes/BIGREST
Author: Leonardo Souza
License: UNKNOWN
Platform: UNKNOWN
Classifier: Programming Language :: Python :: 3
Classifier: License :: OSI Approved :: MIT License
Classifier: Operating System :: OS Independent
Requires-Python: >=3.7
License-File: LICENSE
